[
  { "Id": 1, "Type": "Musicoterapia", "Description": "Sesión de Musicoterapia Individual" },
  { "Id": 2, "Type": "Fisioterapia", "Description": "Control Postural y Movilidad" },
  { "Id": 3, "Type": "Estimulación Multisensorial", "Description": "Estimulación Multisensorial (Sala Snoezelen)" },
  { "Id": 4, "Type": "Logopedia", "Description": "Estimulación de la Comunicación" },
  { "Id": 5, "Type": "Juego Terapéutico", "Description": "Juego Terapéutico con Apoyo Educativo" },
  { "Id": 6, "Type": "Psicomotricidad", "Description": "Psicomotricidad Individual o en Pequeños Grupos" },
  { "Id": 7, "Type": "Fisioterapia", "Description": "Movilización Pasiva y Transferencias Seguras" },
  { "Id": 8, "Type": "Estimulación Visual", "Description": "Estimulación Visual Adaptada" },
  { "Id": 9, "Type": "Estimulación Auditiva", "Description": "Estimulación Auditiva Adaptada" },
  { "Id": 10, "Type": "Hidroterapia", "Description": "Terapia en Entorno Acuático / Hidroterapia" }
]
